{
  "folder": "E4aCGHMCcq65HT4N",
  "name": "Sentir l'Invisible",
  "type": "power",
  "img": "modules/miels-character-importer/media/artwork/vtm5e/icons/auspex.png",
  "_id": "Z5GFjfy6g8URdO6c",
  "system": {
    "description": "<p>Permet de d&eacute;celer l&rsquo;invisible, comme les sorts d&rsquo;Occultation, les utilisateurs d&rsquo;Auspex ou de Sorcellerie du Sang, les fant&ocirc;mes&hellip;<br><br><strong>Jet :</strong> Astuce + Auspex ou R&eacute;solution + Auspex.<br><strong>Co&ucirc;t :&nbsp;</strong>Gratuit.<br><strong>Syst&egrave;me :</strong>&nbsp;Le jet est effectu&eacute; par le conteur ou par le joueur &agrave; l&rsquo;aveugle dans le cas o&ugrave; le vampire tombe nez &agrave; nez avec un &eacute;l&eacute;ment invisible. Si le Descendant cherche activement quelque chose de dissimul&eacute;, le jet devient R&eacute;solution + Auspex.<br><strong>Dur&eacute;e :&nbsp;</strong>Passif.</p>",
    "bonuses": [],
    "discipline": "auspex",
    "duration": "",
    "level": 1,
    "dice1": "wits",
    "dice2": "discipline",
    "cost": "",
    "rollable": true,
    "skill": false,
    "amalgam": false,
    "rouse": false,
    "macroid": ""
  },
  "effects": [],
  "sort": 200000,
  "ownership": {
    "default": 0,
    "Ws85i9GATiQ6bF6s": 3
  },
  "flags": {},
  "_stats": {
    "systemId": "vtm5e",
    "systemVersion": "4.0.1",
    "coreVersion": "11.315",
    "createdTime": 1711804374919,
    "modifiedTime": 1711874937039,
    "lastModifiedBy": "hCCQWghSEZa7MdeI"
  },
  "_key": "!items!Z5GFjfy6g8URdO6c"
}
